README.md
setup.py
yxspkg_songzviewer.py
yxspkg_songzviewer.egg-info/PKG-INFO
yxspkg_songzviewer.egg-info/SOURCES.txt
yxspkg_songzviewer.egg-info/dependency_links.txt
yxspkg_songzviewer.egg-info/entry_points.txt
yxspkg_songzviewer.egg-info/requires.txt
yxspkg_songzviewer.egg-info/top_level.txt