Metadata-Version: 1.1
Name: yxspkg-songzviewer
Version: 1.1.2
Summary: A Image viewer
Home-page: https://github.com/blacksong
Author: blacksong
Author-email: blacksong@yeah.net
License: UNKNOWN
Platform: any
Classifier: Programming Language :: Python :: 3
Classifier: Operating System :: OS Independent
Classifier: Topic :: Software Development :: Libraries :: Python Modules
